[1,["2eTwcsUulPmJmUgl0obNd0"],0,[["sp.SkeletonData",["_name","_atlasText","textureNames","_skeletonJson","textures"],-1,3]],[[0,0,1,2,3,4,5]],[[0,"TX_zhuanguang","\nTX_zhuanguang.png\nsize: 1917,447\nformat: RGBA8888\nfilter: Linear,Linear\nrepeat: none\n1\n  rotate: false\n  xy: 1530, 2\n  size: 233, 225\n  orig: 239, 225\n  offset: 6, 0\n  index: -1\n10\n  rotate: false\n  xy: 681, 270\n  size: 313, 175\n  orig: 352, 188\n  offset: 22, 11\n  index: -1\n11\n  rotate: false\n  xy: 362, 280\n  size: 317, 165\n  orig: 348, 186\n  offset: 26, 11\n  index: -1\n12\n  rotate: false\n  xy: 2, 292\n  size: 358, 153\n  orig: 400, 189\n  offset: 19, 13\n  index: -1\n2\n  rotate: true\n  xy: 1690, 229\n  size: 216, 225\n  orig: 245, 225\n  offset: 6, 0\n  index: -1\n3\n  rotate: false\n  xy: 2, 74\n  size: 299, 216\n  orig: 349, 225\n  offset: 27, 5\n  index: -1\n4\n  rotate: false\n  xy: 619, 48\n  size: 316, 220\n  orig: 347, 225\n  offset: 23, 0\n  index: -1\n5\n  rotate: false\n  xy: 303, 60\n  size: 314, 218\n  orig: 347, 225\n  offset: 24, 0\n  index: -1\n6\n  rotate: false\n  xy: 1190, 5\n  size: 338, 223\n  orig: 387, 225\n  offset: 1, 0\n  index: -1\n7\n  rotate: false\n  xy: 937, 15\n  size: 251, 222\n  orig: 273, 225\n  offset: 0, 3\n  index: -1\n8\n  rotate: false\n  xy: 996, 239\n  size: 292, 206\n  orig: 320, 225\n  offset: 1, 2\n  index: -1\n9\n  rotate: false\n  xy: 1290, 230\n  size: 398, 215\n  orig: 400, 225\n  offset: 0, 0\n  index: -1\n",["TX_zhuanguang.png"],{"skeleton":{"hash":"GRMokKH3sGsEgJUMtlAOEuFYJ2w","spine":"3.8.99","x":-132.51,"y":-250.62,"width":956,"height":900,"images":"","audio":""},"bones":[{"name":"root"}],"slots":[{"name":"1","bone":"root","attachment":"1","blend":"additive"},{"name":"2","bone":"root","blend":"additive"},{"name":"3","bone":"root","blend":"additive"},{"name":"4","bone":"root","blend":"additive"},{"name":"5","bone":"root","blend":"additive"},{"name":"6","bone":"root","blend":"additive"},{"name":"7","bone":"root","blend":"additive"},{"name":"8","bone":"root","blend":"additive"},{"name":"9","bone":"root","blend":"additive"},{"name":"10","bone":"root","blend":"additive"},{"name":"11","bone":"root","blend":"additive"},{"name":"12","bone":"root","blend":"additive"}],"skins":[{"name":"default","attachments":{"1":{"1":{"x":345.49,"y":199.38,"scaleX":4,"scaleY":4,"width":239,"height":225}},"2":{"2":{"x":350.49,"y":167.21,"scaleX":4,"scaleY":4,"width":245,"height":225}},"3":{"3":{"x":132.41,"y":159.81,"scaleX":4,"scaleY":4,"width":349,"height":225}},"4":{"4":{"x":130.89,"y":158.29,"scaleX":4,"scaleY":4,"width":347,"height":225}},"5":{"5":{"x":129.37,"y":162.85,"scaleX":4,"scaleY":4,"width":347,"height":225}},"6":{"6":{"x":3.04,"y":162.85,"scaleX":4,"scaleY":4,"width":387,"height":225}},"7":{"7":{"x":-219.17,"y":143.07,"scaleX":4,"scaleY":4,"width":273,"height":225}},"8":{"8":{"x":-133.94,"y":138.5,"scaleX":4,"scaleY":4,"width":320,"height":225}},"9":{"9":{"x":33.48,"y":167.42,"scaleX":4,"scaleY":4,"width":400,"height":225}},"10":{"10":{"x":121.76,"y":225.26,"scaleX":4,"scaleY":4,"width":352,"height":188}},"11":{"11":{"x":124.8,"y":238.95,"scaleX":4,"scaleY":4,"width":348,"height":186}},"12":{"12":{"x":356.15,"y":234.39,"scaleX":4,"scaleY":4,"width":400,"height":189}}}}],"animations":{"animation":{"slots":{"1":{"attachment":[{"time":0.1,"name":null}]},"2":{"attachment":[{"time":0.1,"name":"2"},{"time":0.2,"name":null}]},"3":{"attachment":[{"time":0.2,"name":"3"},{"time":0.3,"name":null}]},"4":{"attachment":[{"time":0.3,"name":"4"},{"time":0.4,"name":null}]},"5":{"attachment":[{"time":0.4,"name":"5"},{"time":0.5,"name":null}]},"6":{"attachment":[{"time":0.5,"name":"6"},{"time":0.6,"name":null}]},"7":{"attachment":[{"time":0.6,"name":"7"},{"time":0.7,"name":null}]},"8":{"attachment":[{"time":0.7,"name":"8"},{"time":0.8,"name":null}]},"9":{"attachment":[{"time":0.8,"name":"9"},{"time":0.9,"name":null}]},"10":{"attachment":[{"time":0.9,"name":"10"},{"time":1,"name":null}]},"11":{"attachment":[{"time":1,"name":"11"},{"time":1.1,"name":null}]},"12":{"attachment":[{"time":1.1,"name":"12"}]}}}}},[0]]],0,0,[0],[-1],[0]]