[1,["15fxZd2P1Ffbh5sboyBBLb"],0,[["sp.SkeletonData",["_name","_atlasText","textureNames","_skeletonJson","textures"],-1,3]],[[0,0,1,2,3,4,5]],[[0,"jianhun_st_tx1_mj","\njianhun_st_tx1_mj.png\nsize: 1921,224\nformat: RGBA8888\nfilter: Linear,Linear\nrepeat: none\nTX_shangtiao/TX_shangtiao0001\n  rotate: false\n  xy: 1471, 16\n  size: 193, 206\n  orig: 220, 220\n  offset: 21, 0\n  index: -1\nTX_shangtiao/TX_shangtiao0002\n  rotate: false\n  xy: 224, 4\n  size: 209, 218\n  orig: 220, 220\n  offset: 0, 0\n  index: -1\nTX_shangtiao/TX_shangtiao0003\n  rotate: false\n  xy: 2, 2\n  size: 220, 220\n  orig: 220, 220\n  offset: 0, 0\n  index: -1\nTX_shangtiao/TX_shangtiao0004\n  rotate: false\n  xy: 435, 4\n  size: 207, 218\n  orig: 220, 220\n  offset: 0, 0\n  index: -1\nTX_shangtiao/TX_shangtiao0005\n  rotate: false\n  xy: 1666, 16\n  size: 162, 206\n  orig: 220, 220\n  offset: 5, 4\n  index: -1\nTX_shangtiao/TX_shangtiao0006\n  rotate: false\n  xy: 644, 8\n  size: 204, 214\n  orig: 220, 220\n  offset: 0, 0\n  index: -1\nTX_shangtiao/TX_shangtiao0007\n  rotate: false\n  xy: 1057, 14\n  size: 205, 208\n  orig: 220, 220\n  offset: 5, 10\n  index: -1\nTX_shangtiao/TX_shangtiao0008\n  rotate: true\n  xy: 1264, 14\n  size: 208, 205\n  orig: 220, 220\n  offset: 6, 14\n  index: -1\nTX_shangtiao/TX_shangtiao0009\n  rotate: true\n  xy: 850, 12\n  size: 210, 205\n  orig: 220, 220\n  offset: 8, 15\n  index: -1\nTX_shangtiao/TX_shangtiao0010\n  rotate: false\n  xy: 1830, 97\n  size: 89, 125\n  orig: 220, 220\n  offset: 11, 95\n  index: -1\n",["jianhun_st_tx1_mj.png"],{"skeleton":{"hash":"s2BZsjWKm1ONEOY1cM0GytPXbpk","spine":"3.8.99","images":"/guoxue/微信游戏1/游戏项目/dnf/dnf/需替换的/技能/技能改色魔神版/jianhun_st_tx1/images","audio":""},"bones":[{"name":"root","scaleX":-0.5,"scaleY":0.5},{"name":"00","parent":"root","scaleX":0.5,"scaleY":0.5},{"name":"TX_shangtiao","parent":"00","x":610,"y":620,"scaleX":-15.254,"scaleY":14.403},{"name":"Attack","parent":"root"}],"slots":[{"name":"TX_shangtiao/TX_shangtiao0001","bone":"TX_shangtiao"},{"name":"TX_shangtiao","bone":"root","blend":"additive"},{"name":"baishou_shangtiao","bone":"Attack","attachment":"baishou_shangtiao"}],"skins":[{"name":"default","attachments":{"TX_shangtiao/TX_shangtiao0001":{"TX_shangtiao/TX_shangtiao0001":{"x":-9.45,"y":-3.33,"width":220,"height":220},"TX_shangtiao/TX_shangtiao0002":{"x":-9.45,"y":-3.33,"width":220,"height":220},"TX_shangtiao/TX_shangtiao0003":{"x":-9.45,"y":-3.33,"width":220,"height":220},"TX_shangtiao/TX_shangtiao0004":{"x":-9.45,"y":-3.33,"width":220,"height":220},"TX_shangtiao/TX_shangtiao0005":{"x":-9.45,"y":-3.33,"width":220,"height":220},"TX_shangtiao/TX_shangtiao0006":{"x":-9.45,"y":-3.33,"width":220,"height":220},"TX_shangtiao/TX_shangtiao0007":{"x":-9.45,"y":-3.33,"width":220,"height":220},"TX_shangtiao/TX_shangtiao0008":{"x":-9.45,"y":-3.33,"width":220,"height":220},"TX_shangtiao/TX_shangtiao0009":{"x":-9.45,"y":-3.33,"width":220,"height":220},"TX_shangtiao/TX_shangtiao0010":{"x":-9.45,"y":-3.33,"width":220,"height":220}},"baishou_shangtiao":{"baishou_shangtiao":{"type":"boundingbox","vertexCount":4,"color":"60ef00ff","vertices":[-1587.95,1154.04,-424.14,1116.04,-439.54,-662.43,-1599.49,-687.92]}}}}],"events":{"Event_Atk":{}},"animations":{"baishou_shangtiao":{"slots":{"TX_shangtiao/TX_shangtiao0001":{"attachment":[{"time":0.1,"name":"TX_shangtiao/TX_shangtiao0001"},{"time":0.1333,"name":"TX_shangtiao/TX_shangtiao0002"},{"time":0.1667,"name":"TX_shangtiao/TX_shangtiao0003"},{"time":0.2,"name":"TX_shangtiao/TX_shangtiao0004"},{"time":0.2333,"name":"TX_shangtiao/TX_shangtiao0007"},{"time":0.2667,"name":"TX_shangtiao/TX_shangtiao0008"},{"time":0.3,"name":"TX_shangtiao/TX_shangtiao0009"},{"time":0.3333,"name":"TX_shangtiao/TX_shangtiao0010"}]},"baishou_shangtiao":{"attachment":[{"name":null},{"time":0.1333,"name":"baishou_shangtiao"},{"time":0.3,"name":null}]}},"bones":{"TX_shangtiao":{"rotate":[{},{"time":0.1,"angle":-35.13},{"time":0.1333,"angle":5.53},{"time":0.3667,"angle":-0.74}],"scale":[{"time":0.1333},{"time":0.3667,"x":1.071,"y":1.071}]},"Attack":{"translate":[{"time":0.1333,"x":-918.84},{"time":0.2667,"x":-918.84,"y":333.45}],"scale":[{"time":0.1333,"x":-1.357,"y":0.63}]}},"events":[{"time":0.1333,"name":"Event_Atk","string":"TX_shangtiao"}]}}},[0]]],0,0,[0],[-1],[0]]